{"latitude":32.830715,"longitude":-117.1468,"generationtime_ms":1.4514923095703125,"utc_offset_seconds":0,"timezone":"GMT","timezone_abbreviation":"GMT","elevation":133.0,"hourly_units":{"time":"unixtime","temperature_1000hPa":"°C","temperature_975hPa":"°C","temperature_950hPa":"°C","temperature_925hPa":"°C","temperature_900hPa":"°C","temperature_850hPa":"°C","temperature_800hPa":"°C","temperature_700hPa":"°C","temperature_600hPa":"°C","temperature_500hPa":"°C","temperature_400hPa":"°C","temperature_300hPa":"°C","temperature_250hPa":"°C","temperature_200hPa":"°C","temperature_150hPa":"°C","temperature_100hPa":"°C","temperature_70hPa":"°C","temperature_50hPa":"°C","temperature_30hPa":"°C","dew_point_1000hPa":"°C","dew_point_975hPa":"°C","dew_point_950hPa":"°C","dew_point_925hPa":"°C","dew_point_900hPa":"°C","dew_point_850hPa":"°C","dew_point_800hPa":"°C","dew_point_700hPa":"°C","dew_point_600hPa":"°C","dew_point_500hPa":"°C","dew_point_400hPa":"°C","dew_point_300hPa":"°C","dew_point_250hPa":"°C","dew_point_200hPa":"°C","dew_point_150hPa":"°C","dew_point_100hPa":"°C","dew_point_70hPa":"°C","dew_point_50hPa":"°C","dew_point_30hPa":"°C","wind_speed_1000hPa":"kn","wind_speed_975hPa":"kn","wind_speed_950hPa":"kn","wind_speed_925hPa":"kn","wind_speed_900hPa":"kn","wind_speed_850hPa":"kn","wind_speed_800hPa":"kn","wind_speed_700hPa":"kn","wind_speed_600hPa":"kn","wind_speed_500hPa":"kn","wind_speed_400hPa":"kn","wind_speed_300hPa":"kn","wind_speed_250hPa":"kn","wind_speed_200hPa":"kn","wind_speed_150hPa":"kn","wind_speed_100hPa":"kn","wind_speed_70hPa":"kn","wind_speed_50hPa":"kn","wind_speed_30hPa":"kn","wind_direction_1000hPa":"°","wind_direction_975hPa":"°","wind_direction_950hPa":"°","wind_direction_925hPa":"°","wind_direction_900hPa":"°","wind_direction_850hPa":"°","wind_direction_800hPa":"°","wind_direction_700hPa":"°","wind_direction_600hPa":"°","wind_direction_500hPa":"°","wind_direction_400hPa":"°","wind_direction_300hPa":"°","wind_direction_250hPa":"°","wind_direction_200hPa":"°","wind_direction_150hPa":"°","wind_direction_100hPa":"°","wind_direction_70hPa":"°","wind_direction_50hPa":"°","wind_direction_30hPa":"°","geopotential_height_1000hPa":"m","geopotential_height_975hPa":"m","geopotential_height_950hPa":"m","geopotential_height_925hPa":"m","geopotential_height_900hPa":"m","geopotential_height_850hPa":"m","geopotential_height_800hPa":"m","geopotential_height_700hPa":"m","geopotential_height_600hPa":"m","geopotential_height_500hPa":"m","geopotential_height_400hPa":"m","geopotential_height_300hPa":"m","geopotential_height_250hPa":"m","geopotential_height_200hPa":"m","geopotential_height_150hPa":"m","geopotential_height_100hPa":"m","geopotential_height_70hPa":"m","geopotential_height_50hPa":"m","geopotential_height_30hPa":"m","surface_pressure":"hPa"},"hourly":{"time":[1736974800],"temperature_1000hPa":[18.8],"temperature_975hPa":[16.7],"temperature_950hPa":[14.6],"temperature_925hPa":[12.8],"temperature_900hPa":[11.1],"temperature_850hPa":[8.1],"temperature_800hPa":[4.8],"temperature_700hPa":[-2.0],"temperature_600hPa":[-8.8],"temperature_500hPa":[-18.7],"temperature_400hPa":[-29.9],"temperature_300hPa":[-45.0],"temperature_250hPa":[-50.0],"temperature_200hPa":[-51.5],"temperature_150hPa":[-55.5],"temperature_100hPa":[-61.0],"temperature_70hPa":[-61.0],"temperature_50hPa":[-59.5],"temperature_30hPa":[-56.5],"dew_point_1000hPa":[-11.2],"dew_point_975hPa":[-11.9],"dew_point_950hPa":[-13.5],"dew_point_925hPa":[-14.1],"dew_point_900hPa":[-14.6],"dew_point_850hPa":[-17.9],"dew_point_800hPa":[-21.4],"dew_point_700hPa":[-29.6],"dew_point_600hPa":[-36.4],"dew_point_500hPa":[-47.9],"dew_point_400hPa":[-66.0],"dew_point_300hPa":[-67.8],"dew_point_250hPa":[-73.8],"dew_point_200hPa":[-78.6],"dew_point_150hPa":[-80.8],"dew_point_100hPa":[-84.0],"dew_point_70hPa":[-83.4],"dew_point_50hPa":[null],"dew_point_30hPa":[null],"wind_speed_1000hPa":[3.7],"wind_speed_975hPa":[3.3],"wind_speed_950hPa":[3.5],"wind_speed_925hPa":[5.0],"wind_speed_900hPa":[7.7],"wind_speed_850hPa":[14.5],"wind_speed_800hPa":[15.4],"wind_speed_700hPa":[11.3],"wind_speed_600hPa":[5.7],"wind_speed_500hPa":[3.5],"wind_speed_400hPa":[24.8],"wind_speed_300hPa":[12.6],"wind_speed_250hPa":[20.7],"wind_speed_200hPa":[14.8],"wind_speed_150hPa":[14.8],"wind_speed_100hPa":[10.9],"wind_speed_70hPa":[2.0],"wind_speed_50hPa":[8.7],"wind_speed_30hPa":[27.5],"wind_direction_1000hPa":[332],"wind_direction_975hPa":[349],"wind_direction_950hPa":[25],"wind_direction_925hPa":[56],"wind_direction_900hPa":[75],"wind_direction_850hPa":[93],"wind_direction_800hPa":[112],"wind_direction_700hPa":[146],"wind_direction_600hPa":[180],"wind_direction_500hPa":[202],"wind_direction_400hPa":[84],"wind_direction_300hPa":[168],"wind_direction_250hPa":[221],"wind_direction_200hPa":[241],"wind_direction_150hPa":[203],"wind_direction_100hPa":[163],"wind_direction_70hPa":[162],"wind_direction_50hPa":[117],"wind_direction_30hPa":[71],"geopotential_height_1000hPa":[172.00],"geopotential_height_975hPa":[388.00],"geopotential_height_950hPa":[608.00],"geopotential_height_925hPa":[832.00],"geopotential_height_900hPa":[1061.00],"geopotential_height_850hPa":[1534.00],"geopotential_height_800hPa":[2030.00],"geopotential_height_700hPa":[3103.00],"geopotential_height_600hPa":[4312.00],"geopotential_height_500hPa":[5696.00],"geopotential_height_400hPa":[7320.99],"geopotential_height_300hPa":[9301.61],"geopotential_height_250hPa":[10502.86],"geopotential_height_200hPa":[11951.16],"geopotential_height_150hPa":[13802.98],"geopotential_height_100hPa":[16341.67],"geopotential_height_70hPa":[18568.31],"geopotential_height_50hPa":[20641.38],"geopotential_height_30hPa":[23878.51],"surface_pressure":[1004.9]}}